sparkey/__init__.py
sparkey_python-0.3.0.dist-info/LICENSE
sparkey_python-0.3.0.dist-info/METADATA
sparkey_python-0.3.0.dist-info/NOTICE
sparkey_python-0.3.0.dist-info/WHEEL
sparkey_python-0.3.0.dist-info/top_level.txt
sparkey_python-0.3.0.dist-info/RECORD
