Metadata-Version: 2.1
Name: sparkey-python
Version: 0.3.0
Summary: Python bindings for Sparkey
Author: Kristofer Karlsson
Author-email: krka@spotify.com
License: Apache Software License 2.0
Classifier: Topic :: Database
Classifier: Intended Audience :: Developers
Classifier: License :: OSI Approved :: Apache Software License
License-File: LICENSE
License-File: NOTICE
Requires-Dist: future==1.0.0
